pyRosita/version.py
pyRosita-0.0.1.dist-info/LICENSE
pyRosita-0.0.1.dist-info/METADATA
pyRosita-0.0.1.dist-info/WHEEL
pyRosita-0.0.1.dist-info/top_level.txt
pyRosita-0.0.1.dist-info/RECORD
